bfabric/__init__.py
bfabric/bfabric.py
bfabric/errors.py
bfabric/py.typed
bfabric/typing.py
bfabric/config/__init__.py
bfabric/config/bfabric_auth.py
bfabric/config/bfabric_client_config.py
bfabric/config/config_data.py
bfabric/config/config_file.py
bfabric/engine/__init__.py
bfabric/engine/engine_suds.py
bfabric/engine/engine_zeep.py
bfabric/engine/response_format_suds.py
bfabric/entities/__init__.py
bfabric/entities/application.py
bfabric/entities/dataset.py
bfabric/entities/executable.py
bfabric/entities/externaljob.py
bfabric/entities/instrument.py
bfabric/entities/multiplexid.py
bfabric/entities/multiplexkit.py
bfabric/entities/order.py
bfabric/entities/parameter.py
bfabric/entities/plate.py
bfabric/entities/project.py
bfabric/entities/resource.py
bfabric/entities/run.py
bfabric/entities/sample.py
bfabric/entities/storage.py
bfabric/entities/user.py
bfabric/entities/workflow.py
bfabric/entities/workflowstep.py
bfabric/entities/workflowtemplate.py
bfabric/entities/workflowtemplatestep.py
bfabric/entities/workunit.py
bfabric/entities/cache/__init__.py
bfabric/entities/cache/_cache_stack.py
bfabric/entities/cache/_entity_memory_cache.py
bfabric/entities/cache/_fifo_cache.py
bfabric/entities/cache/context.py
bfabric/entities/core/__init__.py
bfabric/entities/core/entity.py
bfabric/entities/core/entity_reader.py
bfabric/entities/core/has_many.py
bfabric/entities/core/has_one.py
bfabric/entities/core/import_entity.py
bfabric/entities/core/references.py
bfabric/entities/core/uri.py
bfabric/entities/core/users.py
bfabric/entities/core/mixins/__init__.py
bfabric/entities/core/mixins/entity_mixin_protocol.py
bfabric/entities/core/mixins/find_mixin.py
bfabric/entities/core/mixins/user_created_mixin.py
bfabric/examples/compare_zeep_suds_pagination.py
bfabric/examples/compare_zeep_suds_query.py
bfabric/examples/exists_multi.py
bfabric/examples/zeep_debug.py
bfabric/experimental/README.md
bfabric/experimental/__init__.py
bfabric/experimental/dataset_column_types.py
bfabric-1.16.1.dist-info/METADATA
bfabric-1.16.1.dist-info/WHEEL
bfabric-1.16.1.dist-info/RECORD
