Metadata-Version: 2.4
Name: bfabric
Version: 1.16.1
Summary: Python client for the B-Fabric API
Project-URL: Homepage, https://github.com/fgcz/bfabricPy
Project-URL: Repository, https://github.com/fgcz/bfabricPy
Author: Aleksejs Fomins, Marco Schmidt, Maria d'Errico, Witold Eryk Wolski
Author-email: Christian Panse <cp@fgcz.ethz.ch>, Leonardo Schwarz <leonardo.schwarz@fgcz.ethz.ch>
License: GPL-3.0
Requires-Python: >=3.11
Requires-Dist: annotated-types>=0.7.0
Requires-Dist: eval-type-backport; python_version < '3.10'
Requires-Dist: httpx<0.29,>=0.28.1
Requires-Dist: loguru<0.8,>=0.7
Requires-Dist: polars-lts-cpu<2.0,>=1.30; platform_machine == 'x86_64' and platform_system == 'Darwin'
Requires-Dist: polars<2.0,>=1.30; platform_machine != 'x86_64' or platform_system != 'Darwin'
Requires-Dist: pydantic<3.0,>=2.9.2
Requires-Dist: python-dateutil<3.0,>=2.9.0
Requires-Dist: pyyaml<7.0,>=6.0.2
Requires-Dist: requests<3.0,>=2.27.0
Requires-Dist: rich<15.0.0,>=14.0.0
Requires-Dist: suds<2.0.0,>=1.2.0
Requires-Dist: zeep<5.0,>=4.3.2
Provides-Extra: dev
Requires-Dist: black; extra == 'dev'
Requires-Dist: coverage>=7.10.0; extra == 'dev'
Requires-Dist: dirty-equals>=0.10.0; extra == 'dev'
Requires-Dist: ipython; extra == 'dev'
Requires-Dist: isort; extra == 'dev'
Requires-Dist: licensecheck; extra == 'dev'
Requires-Dist: logot[loguru,pytest]>=1.5.1; extra == 'dev'
Requires-Dist: mkdocs; extra == 'dev'
Requires-Dist: mkdocs-material; extra == 'dev'
Requires-Dist: mkdocstrings[python]; extra == 'dev'
Requires-Dist: nox>=2025.11.12; extra == 'dev'
Requires-Dist: pytest-asyncio>=1.2.0; extra == 'dev'
Requires-Dist: pytest-mock>=3.15; extra == 'dev'
Requires-Dist: pytest>=8; extra == 'dev'
Requires-Dist: ruff; extra == 'dev'
Requires-Dist: uv; extra == 'dev'
Provides-Extra: doc
Requires-Dist: mkdocs; extra == 'doc'
Requires-Dist: mkdocs-material; extra == 'doc'
Requires-Dist: mkdocstrings[python]; extra == 'doc'
Provides-Extra: test
Requires-Dist: coverage>=7.10.0; extra == 'test'
Requires-Dist: dirty-equals>=0.10.0; extra == 'test'
Requires-Dist: logot[loguru,pytest]>=1.5.1; extra == 'test'
Requires-Dist: pytest-asyncio>=1.2.0; extra == 'test'
Requires-Dist: pytest-mock>=3.15; extra == 'test'
Requires-Dist: pytest>=8; extra == 'test'
Provides-Extra: typing
Requires-Dist: lxml-stubs; extra == 'typing'
Requires-Dist: mypy; extra == 'typing'
Requires-Dist: types-python-dateutil; extra == 'typing'
Requires-Dist: types-pyyaml; extra == 'typing'
Requires-Dist: types-requests; extra == 'typing'
